GXN/__init__.py
GXN/gxn.py
GXN/data/__init__.py
GXN/data/GO/__init__.py
GXN/data/GO/go-basic.obo
GXN/data/GO/go_loader.py
GXN/data/GO/goslim_generic.obo
GXN/data/iDog/__init__.py
GXN/data/iDog/configuration.py
GXN/data/iDog/gene_expression.py
GXN/data/iDog/go.py
GXN/data/iDog/tf.py
GXN/data/iDog/tissues.py
GXN/data/iDog/data/Canis_familiaris_TF.txt
GXN/data/iDog/data/Canis_familiaris_TF_cofactors.txt
GXN/data/iDog/data/gene_expression_matrix.csv
GXN/data/iDog/data/mart_export.txt
GXN/data/iDog/data/tissues_clean.csv
GXN/data/iHuman/__init__.py
GXN/data/iHuman/configuration.py
GXN/data/iHuman/gene_expression.py
GXN/data/iHuman/go.py
GXN/data/iHuman/tf.py
GXN/data/iHuman/tissues.py
GXN/data/iHuman/data/465_lymphoblastoid_cell_lines.zip
GXN/data/iHuman/data/Homo_sapiens_TF.txt
GXN/data/iHuman/data/Homo_sapiens_TF_cofactors.txt
GXN/data/iHuman/data/Human_developmental_biology_resource.zip
GXN/data/iHuman/data/macrophage_immune_response.zip
GXN/data/iHuman/data/mart_export.txt
GXN/data/iHuman/data/sensory_neurons_IPS.zip
GXN/data/iHuman/data/BRAIN/DonorInformation.csv
GXN/data/iHuman/data/BRAIN/columns-samples.csv
GXN/data/iHuman/data/BRAIN/kegg_alzheimer.csv
GXN/data/iHuman/data/BRAIN/rows-genes.csv
GXN/data/iRat/__init__.py
GXN/data/iRat/configuration.py
GXN/data/iRat/gene_expression.py
GXN/data/iRat/go.py
GXN/data/iRat/tf.py
GXN/data/iRat/tissues.py
GXN/data/iRat/data/Rattus_norvegicus_TF.txt
GXN/data/iRat/data/Rattus_norvegicus_TF_cofactors.txt
GXN/data/iRat/data/mart_export.txt
GXN/data/iRat/data/eleven_organs_four_stages/E-GEOD-53960-experiment-design.tsv
GXN/data/iRat/data/eleven_organs_four_stages/E-GEOD-53960-query-results.tpms.tsv
GXN/data/iRat/data/eleven_organs_four_stages/source.txt
GXN-0.0.30.dist-info/LICENSE
GXN-0.0.30.dist-info/METADATA
GXN-0.0.30.dist-info/WHEEL
GXN-0.0.30.dist-info/top_level.txt
GXN-0.0.30.dist-info/RECORD
