Metadata-Version: 2.1
Name: GXN
Version: 0.0.30
Summary: Generalizable Gene Self-Expressive Networks
Home-page: 
Author: Sergio Peignier
Author-email: sergio.peignier@insa-lyon.fr
Classifier: Programming Language :: Python :: 3
Classifier: License :: OSI Approved :: GNU General Public License (GPL)
Classifier: Operating System :: OS Independent
License-File: LICENSE
Requires-Dist: pandas
Requires-Dist: numpy
Requires-Dist: scikit-learn
Requires-Dist: tqdm
Requires-Dist: scipy
Requires-Dist: gseapy
Requires-Dist: goatools
Requires-Dist: kneed
Requires-Dist: pygraphviz
Requires-Dist: networkx
Requires-Dist: grenadine
